MANIFEST.in
README.rst
setup.cfg
setup.py
all_search_module/__init__.py
all_search_module/index.py
all_search_module/originals_index.py
all_search_module/paginationspellcheck.py
all_search_module/sub.py
all_search_module/sub_gp.py
all_search_module/urls.py
all_search_module/utils.py
all_search_module.egg-info/PKG-INFO
all_search_module.egg-info/SOURCES.txt
all_search_module.egg-info/dependency_links.txt
all_search_module.egg-info/requires.txt
all_search_module.egg-info/top_level.txt
all_search_module/eswrapper/__init__.py
all_search_module/eswrapper/defines.py
all_search_module/eswrapper/eswrapper.py
all_search_module/eswrapper/originals_defines.py
all_search_module/eswrapper/originals_eswrapper.py
all_search_module/eswrapper/settings.py
all_search_module/eswrapper/utils.py
all_search_module/script/__init__.py
all_search_module/script/aliastoindex.py
all_search_module/script/gpindex.py
all_search_module/script/updateindex.py